element_optogenetics/__init__.py
element_optogenetics/optogenetics.py
element_optogenetics/version.py
element_optogenetics-0.1.3.dist-info/LICENSE
element_optogenetics-0.1.3.dist-info/METADATA
element_optogenetics-0.1.3.dist-info/WHEEL
element_optogenetics-0.1.3.dist-info/top_level.txt
element_optogenetics-0.1.3.dist-info/RECORD
