Metadata-Version: 2.1
Name: element-optogenetics
Version: 0.1.3
Summary: DataJoint Element for Optogenetics
Home-page: https://github.com/datajoint/element-optogenetics
Author: DataJoint
Author-email: info@datajoint.com
License: MIT
Keywords: neuroscience optogenetics science datajoint
Platform: UNKNOWN
License-File: LICENSE
Requires-Dist: datajoint (>=0.13.0)
